{"id":"black.trans","path":"/home/robin/werk/Eigen/typedal/venv/lib/python3.10/site-packages/black/trans.py","mtime":1716403960,"size":95476,"hash":"b284d09bc46948a47d9cd78fb0ae5ae22a1c4da1340f0722c3bd2244aab3f1af","data_mtime":1716403972,"dependencies":["black.comments","black.lines","black.mode","black.nodes","black.rusty","black.strings","re","abc","collections","dataclasses","typing","mypy_extensions","builtins","pyexpat.model","pyexpat.errors","_typeshed","black.brackets","enum","types","typing_extensions"],"suppressed":["blib2to3.pgen2","blib2to3.pytree"],"options":{"ignore_errors":false,"disable_error_code":["misc"],"implicit_optional":true,"disallow_any_generics":true,"strict_concatenate":false,"disallow_subclassing_any":true,"disallow_untyped_defs":true,"disallow_untyped_calls":true,"check_untyped_defs":true,"ignore_missing_imports":true,"disallow_incomplete_defs":true,"disallow_any_expr":false,"plugins":[],"enable_error_code":[],"follow_imports_for_stubs":false,"bazel":false,"disallow_any_explicit":false,"disable_memoryview_promotion":false,"follow_imports":"normal","always_true":[],"always_false":[],"implicit_reexport":false,"disable_bytearray_promotion":false,"enabled_error_codes":[],"local_partial_types":false,"disallow_untyped_decorators":true,"disabled_error_codes":["misc"],"allow_untyped_globals":false,"warn_unused_ignores":true,"strict_equality":true,"platform":"linux","old_type_inference":false,"warn_no_return":true,"strict_optional":true,"disallow_any_decorated":false,"warn_unreachable":false,"warn_return_any":true,"allow_redefinition":false,"disallow_any_unimported":false,"mypyc":false,"extra_checks":true},"dep_prios":[5,5,5,5,5,5,10,5,5,5,5,5,5,20,20,30,30,30,30,30,5,5],"dep_lines":[30,31,32,33,45,46,5,6,7,8,9,28,1,1,1,1,1,1,1,1,54,55],"interface_hash":"68af39ea3122a5df9be44d036abb56b9d9ff358b41c2e4ef5edd345cef179165","version_id":"1.10.0","ignore_all":true,"plugin_data":null}